<?xml version="1.0"?>
<opencv_storage>
<calibration_Time>"Monday 26 September 2016 09:01:29 PM IST"</calibration_Time>
<nrOfFrames>25</nrOfFrames>
<image_Width>640</image_Width>
<image_Height>480</image_Height>
<board_Width>6</board_Width>
<board_Height>5</board_Height>
<square_Size>37.</square_Size>
<FixAspectRatio>1.</FixAspectRatio>
<!-- flags:  +fix_aspectRatio +fix_principal_point +zero_tangent_dist -->
<flagValue>14</flagValue>
<Camera_Matrix type_id="opencv-matrix">
  <rows>3</rows>
  <cols>3</cols>
  <dt>d</dt>
  <data>
    6.7874081912716247e+02 0. 3.1950000000000000e+02 0.
    6.7874081912716247e+02 2.3950000000000000e+02 0. 0. 1.</data></Camera_Matrix>
<Distortion_Coefficients type_id="opencv-matrix">
  <rows>5</rows>
  <cols>1</cols>
  <dt>d</dt>
  <data>
    -5.4687360954866225e-02 2.0006865925562323e-01 0. 0.
    -1.0743225065513928e+00</data></Distortion_Coefficients>
<Avg_Reprojection_Error>4.9078767990323935e-01</Avg_Reprojection_Error>
<Per_View_Reprojection_Errors type_id="opencv-matrix">
  <rows>25</rows>
  <cols>1</cols>
  <dt>f</dt>
  <data>
    5.61842918e-01 8.27190101e-01 2.00982898e-01 3.21328253e-01
    1.21666777e+00 3.34181160e-01 2.84658343e-01 2.65789688e-01
    1.79271623e-01 2.51159579e-01 3.50044340e-01 2.01231003e-01
    2.25877196e-01 2.24739760e-01 9.02891815e-01 2.44217992e-01
    5.54056823e-01 1.83001772e-01 4.65272665e-01 6.80241525e-01
    3.21064860e-01 4.37119514e-01 4.32359040e-01 4.37844038e-01
    4.55545813e-01</data></Per_View_Reprojection_Errors>
<!-- a set of 6-tuples (rotation vector + translation vector) for each view -->
<Extrinsic_Parameters type_id="opencv-matrix">
  <rows>25</rows>
  <cols>6</cols>
  <dt>d</dt>
  <data>
    -1.6630069987332186e-01 -1.7025814584430810e-01
    -1.5137231904874375e+00 -1.8533049843933691e+02
    2.0686596983576382e+02 8.3386280626433950e+02 1.7792330770138400e-03
    4.9652256600442722e-02 2.0928842795526741e+00
    -7.8046503633597297e+01 -7.7316130594933028e+01
    8.7913011470007893e+02 -2.6928718764245330e-01
    -3.1516805182228375e-01 -1.0670235580140766e-01
    -4.6920868896511229e+02 -9.8160730552904791e+00
    1.2278292385841573e+03 -2.9992163503510200e-01
    4.1175728792351146e-01 2.9931112393267028e+00 2.0868787613111601e+02
    -3.8840614533733543e+01 6.2418862916808291e+02
    1.7069193757352011e-01 -3.5266284896844996e-02
    2.8793179653421944e-02 -9.5758763231931052e+00
    -1.1511230869664566e+02 4.7751975449779491e+02
    3.2474866569048272e-01 -2.5895846379347948e-01
    1.5607078835532313e+00 1.1927192913990680e+02
    -1.1595458025457502e+02 4.1553305904507721e+02
    3.1438467485179228e-01 3.3211087837441831e-02
    -1.1843035258732653e-02 -2.8756405151295684e+01
    -8.0563094401542045e+01 4.4746573300010488e+02
    3.1943437442785144e-01 3.3796536886939746e-02
    -1.2335034858732736e-02 -2.8230467876690053e+01
    -8.0091164731848465e+01 4.4637333645020544e+02
    2.8867091734171918e-01 2.6416990572308299e-02
    -1.4266271969732144e-02 -2.8703269749416013e+01
    -8.5738635575651585e+01 4.5595315755448280e+02
    2.7556061693028927e-01 2.2723357155123310e-02
    -1.1518901491255644e-02 -3.0280715996069379e+01
    -8.1890178845643760e+01 4.5731555241919079e+02
    2.6067740024381975e-01 4.0613671186673556e-02
    -1.3904283797496348e-02 -2.8322009224304267e+01
    -8.5878322471840377e+01 4.6711817442633776e+02
    2.5543710071834397e-01 2.3825447925846798e-02
    -1.4631049131213278e-02 -2.8321325308126358e+01
    -8.9570585234149888e+01 4.6488637735191793e+02
    2.4793380480323599e-01 3.1108323257817934e-02
    -1.7977458429938937e-02 -2.8181486049478554e+01
    -8.9401467538728667e+01 4.6782748676216312e+02
    2.3463959614822530e-01 2.8306500534356099e-02
    -1.6469081708505445e-02 -3.0026286708237418e+01
    -8.6901228344230830e+01 4.7162369689840500e+02
    7.7066323659768732e-02 3.5361259047414850e-01
    -4.4319327155988207e-02 3.7273003390940489e+00
    -1.0362388384176087e+02 4.9665220684850777e+02
    8.0108801333854429e-01 8.8857812995127183e-02
    -3.0015976146745973e+00 -4.1694644101387119e+00
    9.9230218872099769e+01 5.7765519425702155e+02 1.0492520087789683e-01
    2.6762313354906753e-01 -3.0869652493788204e+00
    8.7107686254201411e+01 1.0364369807656475e+02 4.6659723983908231e+02
    1.7334510181783713e-01 2.2191765282107975e-01
    -3.0811251020997013e+00 8.5633785895178562e+01
    9.0764057870759444e+01 4.3922356745303455e+02 2.7285575264476536e-01
    7.8416116903230651e-02 -3.0668124634754355e+00
    4.1425343307264001e+01 9.7129031278870642e+01 4.6461940426480146e+02
    4.8396911355508598e-01 -1.4043810557138700e-01
    -3.0202986557675642e+00 4.6122906834481618e+00
    7.7549081479595074e+01 5.1988148908120013e+02 3.3919057100955480e-01
    -3.7962598354258065e-01 -1.3853378490674830e+00
    -1.7438673813106550e+02 9.7407022877260616e+01
    4.5951404423668811e+02 3.8863462570382790e-01
    -4.3587337557684064e-01 -1.4353001653322952e+00
    -1.7740199374012593e+02 1.0470848978122547e+02
    4.3811974980632556e+02 4.0410598476113246e-01
    -4.1496535659753031e-01 -1.4317228157197477e+00
    -1.7103495189104120e+02 1.0380027502008588e+02
    4.3390190457059759e+02 4.0346505385139148e-01
    -4.1438010856498547e-01 -1.4324447175167219e+00
    -1.7050862838828928e+02 1.0502537580896654e+02
    4.3413881311971500e+02 4.0107921038625771e-01
    -4.1970157936060887e-01 -1.4290315744155746e+00
    -1.7164470463781214e+02 1.0855238327387227e+02
    4.3368443106680104e+02</data></Extrinsic_Parameters>
<Image_points type_id="opencv-matrix">
  <rows>25</rows>
  <cols>30</cols>
  <dt>"2f"</dt>
  <data>
    1.69562683e+02 4.06665894e+02 1.71903107e+02 3.77373596e+02
    1.74754074e+02 3.46750366e+02 1.77468521e+02 3.18326324e+02
    1.80250153e+02 2.87739227e+02 1.82620224e+02 2.60487152e+02
    1.98990616e+02 4.09079590e+02 2.02027344e+02 3.77905853e+02
    2.03929535e+02 3.48933228e+02 2.06724442e+02 3.18348785e+02
    2.09129303e+02 2.90648438e+02 2.11311554e+02 2.60568726e+02
    2.29534790e+02 4.09839905e+02 2.31127640e+02 3.80175110e+02
    2.33836563e+02 3.49465240e+02 2.35820114e+02 3.20892639e+02
    2.38116882e+02 2.91081207e+02 2.40454361e+02 2.63326996e+02
    2.58310730e+02 4.11603485e+02 2.61034485e+02 3.81357971e+02
    2.62664368e+02 3.51361389e+02 2.65084381e+02 3.21781616e+02
    2.67400299e+02 2.93402222e+02 2.68832001e+02 2.63905853e+02
    2.89069763e+02 4.13240265e+02 2.90276886e+02 3.82710144e+02
    2.92659119e+02 3.52566956e+02 2.94008118e+02 3.23274689e+02
    2.95996368e+02 2.94294434e+02 2.98353943e+02 2.65762268e+02
    2.60216370e+02 1.79914963e+02 2.45536804e+02 2.04667313e+02
    2.30862640e+02 2.29545837e+02 2.15665756e+02 2.53917755e+02
    2.01083633e+02 2.78568695e+02 1.85392975e+02 3.02355164e+02
    2.35588425e+02 1.65606201e+02 2.21183685e+02 1.90461655e+02
    2.06569366e+02 2.15153046e+02 1.92217026e+02 2.39768417e+02
    1.77192596e+02 2.64228973e+02 1.63941376e+02 2.89365814e+02
    2.10696152e+02 1.51592850e+02 1.96351898e+02 1.76393036e+02
    1.81868134e+02 2.00903366e+02 1.67342941e+02 2.25499435e+02
    1.53414886e+02 2.50167038e+02 1.38325165e+02 2.74516937e+02
    1.85800552e+02 1.37787323e+02 1.71821915e+02 1.62609558e+02
    1.57287994e+02 1.87039520e+02 1.43020538e+02 2.11353653e+02
    1.28814438e+02 2.36265656e+02 1.16193672e+02 2.61208435e+02
    1.61066010e+02 1.23820663e+02 1.46932022e+02 1.48930344e+02
    1.32888947e+02 1.72996979e+02 1.18602196e+02 1.97848221e+02
    1.04323288e+02 2.21577118e+02 9.14358063e+01 2.47898849e+02
    6.15388298e+01 2.33984497e+02 8.30230865e+01 2.32836884e+02
    1.03937401e+02 2.31703812e+02 1.24604561e+02 2.30560120e+02
    1.44942337e+02 2.29430359e+02 1.64784943e+02 2.28303650e+02
    6.27780113e+01 2.53805679e+02 8.41297073e+01 2.52502151e+02
    1.05576874e+02 2.51115204e+02 1.26168228e+02 2.49658127e+02
    1.46497269e+02 2.48404007e+02 1.66516464e+02 2.47106354e+02
    6.39957504e+01 2.73621826e+02 8.57353287e+01 2.72218231e+02
    1.06826653e+02 2.70524139e+02 1.27729462e+02 2.69052612e+02
    1.48205048e+02 2.67538544e+02 1.68246933e+02 2.66017212e+02
    6.51760330e+01 2.93759186e+02 8.68990555e+01 2.91929749e+02
    1.08166809e+02 2.90267120e+02 1.29263031e+02 2.88526428e+02
    1.49518021e+02 2.86905640e+02 1.69866165e+02 2.85340546e+02
    6.63325958e+01 3.14151947e+02 8.82330399e+01 3.12134918e+02
    1.09580505e+02 3.10265900e+02 1.30773743e+02 3.08365356e+02
    1.51102158e+02 3.06505920e+02 1.71495789e+02 3.04587769e+02
    5.45179932e+02 1.97855255e+02 5.08613098e+02 2.00173370e+02
    4.71219330e+02 2.02750580e+02 4.32744965e+02 2.05223679e+02
    3.93229584e+02 2.07899597e+02 3.52422607e+02 2.10685440e+02
    5.36664490e+02 1.60591156e+02 5.00697754e+02 1.62489120e+02
    4.63451172e+02 1.64529526e+02 4.25760132e+02 1.66500107e+02
    3.86500214e+02 1.68633316e+02 3.46434082e+02 1.71024704e+02
    5.28549072e+02 1.24443886e+02 4.92918274e+02 1.25799850e+02
    4.56266937e+02 1.27426086e+02 4.18830566e+02 1.28801010e+02
    3.80383026e+02 1.30603775e+02 3.40382385e+02 1.32472534e+02
    5.20226562e+02 8.96715698e+01 4.85293182e+02 9.03976593e+01
    4.48898560e+02 9.14541931e+01 4.12189453e+02 9.25314102e+01
    3.73586090e+02 9.38646011e+01 3.35177063e+02 9.54750443e+01
    5.12115784e+02 5.56508217e+01 4.77397095e+02 5.59890099e+01
    4.41869751e+02 5.66709671e+01 4.05232269e+02 5.72132034e+01
    3.68091919e+02 5.85361176e+01 3.28238800e+02 5.94449348e+01
    3.07835327e+02 7.59601059e+01 3.58452759e+02 7.83180389e+01
    4.10133575e+02 7.88723907e+01 4.60910461e+02 8.11963425e+01
    5.12453430e+02 8.20678635e+01 5.63155884e+02 8.41673508e+01
    3.05900543e+02 1.29616501e+02 3.56578918e+02 1.30550049e+02
    4.06794098e+02 1.32787704e+02 4.57879211e+02 1.33674911e+02
    5.08051971e+02 1.35558258e+02 5.58962646e+02 1.36824738e+02
    3.04777130e+02 1.80531204e+02 3.53815887e+02 1.83500916e+02
    4.04561798e+02 1.84024689e+02 4.53878571e+02 1.86313416e+02
    5.04349091e+02 1.87001266e+02 5.53855957e+02 1.89162628e+02
    3.02420197e+02 2.32645050e+02 3.52463898e+02 2.33157425e+02
    4.01330902e+02 2.35209534e+02 4.51257721e+02 2.35962830e+02
    4.99944153e+02 2.37856461e+02 5.49848022e+02 2.38679977e+02
    3.01951935e+02 2.80352173e+02 3.50170105e+02 2.82478027e+02
    3.99419006e+02 2.83452301e+02 4.47752014e+02 2.85293732e+02
    4.96654785e+02 2.86132263e+02 5.45249573e+02 2.87700012e+02
    5.12409912e+02 5.17679901e+01 5.06640289e+02 1.11503891e+02
    5.01310150e+02 1.67901031e+02 4.95890442e+02 2.20950211e+02
    4.90858246e+02 2.71036865e+02 4.85983704e+02 3.18292267e+02
    4.52752930e+02 5.08853912e+01 4.48747772e+02 1.10752594e+02
    4.44954834e+02 1.67171173e+02 4.41276062e+02 2.20246185e+02
    4.37722351e+02 2.70254852e+02 4.34455841e+02 3.17487183e+02
    3.92875336e+02 4.99246254e+01 3.90568420e+02 1.09752800e+02
    3.88478577e+02 1.66204697e+02 3.86523499e+02 2.19343796e+02
    3.84541992e+02 2.69327667e+02 3.82661743e+02 3.16394379e+02
    3.32966370e+02 4.91740341e+01 3.32490021e+02 1.08957352e+02
    3.31985596e+02 1.65275497e+02 3.31550659e+02 2.18386353e+02
    3.31264832e+02 2.68167084e+02 3.30961212e+02 3.15329865e+02
    2.73229462e+02 4.85697136e+01 2.74538788e+02 1.08114876e+02
    2.75813293e+02 1.64308350e+02 2.77112915e+02 2.17148041e+02
    2.78298859e+02 2.67073700e+02 2.79381500e+02 3.14310394e+02
    2.75523621e+02 1.16859436e+02 3.31725647e+02 1.16454681e+02
    3.88355469e+02 1.15938049e+02 4.44889709e+02 1.15520683e+02
    5.01289459e+02 1.15024231e+02 5.57624573e+02 1.14531448e+02
    2.77630646e+02 1.72270111e+02 3.32535461e+02 1.71891937e+02
    3.87667755e+02 1.71519989e+02 4.42880096e+02 1.71211700e+02
    4.97835144e+02 1.70562805e+02 5.53068848e+02 1.70247055e+02
    2.79696960e+02 2.24611755e+02 3.33307861e+02 2.24634399e+02
    3.87182953e+02 2.24342834e+02 4.40805634e+02 2.23838470e+02
    4.94507080e+02 2.23461975e+02 5.48378235e+02 2.22995285e+02
    2.81634491e+02 2.74561310e+02 3.33926025e+02 2.74575195e+02
    3.86413940e+02 2.74393127e+02 4.38834778e+02 2.74147461e+02
    4.91224182e+02 2.73596527e+02 5.43690674e+02 2.73375153e+02
    2.83568481e+02 3.22105804e+02 3.34563599e+02 3.21963104e+02
    3.85731659e+02 3.21916779e+02 4.36895599e+02 3.21729767e+02
    4.87964081e+02 3.21460266e+02 5.39335144e+02 3.21223083e+02
    2.76216278e+02 1.17353577e+02 3.32630432e+02 1.16852348e+02
    3.89314850e+02 1.16368416e+02 4.46047394e+02 1.15939003e+02
    5.02555237e+02 1.15396049e+02 5.59146851e+02 1.14892159e+02
    2.78377045e+02 1.72583008e+02 3.33383179e+02 1.72406219e+02
    3.88632690e+02 1.71941986e+02 4.43910553e+02 1.71528046e+02
    4.99059326e+02 1.71011780e+02 5.54387878e+02 1.70534683e+02
    2.80449127e+02 2.25107498e+02 3.34154053e+02 2.25185608e+02
    3.88052429e+02 2.24634384e+02 4.41855560e+02 2.24379471e+02
    4.95622772e+02 2.23752869e+02 5.49595886e+02 2.23429825e+02
    2.82416595e+02 2.74999451e+02 3.34756500e+02 2.75114899e+02
    3.87351257e+02 2.74770691e+02 4.39773315e+02 2.74504608e+02
    4.92294678e+02 2.74072601e+02 5.44923767e+02 2.73708862e+02
    2.84399994e+02 3.22454803e+02 3.35436096e+02 3.22385406e+02
    3.86638000e+02 3.22383270e+02 4.37824646e+02 3.22144836e+02
    4.89028503e+02 3.21784210e+02 5.40427307e+02 3.21480621e+02
    2.76635712e+02 1.11743866e+02 3.31699188e+02 1.11170319e+02
    3.87117462e+02 1.10386452e+02 4.42501526e+02 1.09719330e+02
    4.97638397e+02 1.09011612e+02 5.52872681e+02 1.08344742e+02
    2.78603943e+02 1.66356369e+02 3.32471222e+02 1.65700806e+02
    3.86591827e+02 1.65042831e+02 4.40723022e+02 1.64495361e+02
    4.94721497e+02 1.63787872e+02 5.48939819e+02 1.63201965e+02
    2.80454132e+02 2.18309174e+02 3.33192200e+02 2.17981613e+02
    3.86192047e+02 2.17425354e+02 4.39167664e+02 2.16917450e+02
    4.91778687e+02 2.16115417e+02 5.44834900e+02 2.15622818e+02
    2.82324219e+02 2.68093567e+02 3.33957703e+02 2.67831879e+02
    3.85690338e+02 2.67447083e+02 4.37436951e+02 2.66952271e+02
    4.89064423e+02 2.66356171e+02 5.40882812e+02 2.65761902e+02
    2.84109863e+02 3.15715942e+02 3.34591888e+02 3.15508057e+02
    3.85237762e+02 3.15241516e+02 4.35796051e+02 3.14791473e+02
    4.86338745e+02 3.14311432e+02 5.37063232e+02 3.13752228e+02
    2.74405457e+02 1.17706596e+02 3.29296997e+02 1.17236237e+02
    3.84466644e+02 1.16591782e+02 4.39616211e+02 1.16163841e+02
    4.94601044e+02 1.15500259e+02 5.49622070e+02 1.15020027e+02
    2.76190979e+02 1.72258011e+02 3.30008118e+02 1.71820084e+02
    3.83998230e+02 1.71337524e+02 4.38003693e+02 1.70860138e+02
    4.91716309e+02 1.70285065e+02 5.45737488e+02 1.69711273e+02
    2.78083862e+02 2.24197021e+02 3.30611206e+02 2.24145294e+02
    3.83528259e+02 2.23600708e+02 4.36195892e+02 2.23231171e+02
    4.88912048e+02 2.22600708e+02 5.41739502e+02 2.22152390e+02
    2.79697174e+02 2.74130798e+02 3.31336121e+02 2.74001770e+02
    3.83008911e+02 2.73594238e+02 4.34634644e+02 2.73284576e+02
    4.86027893e+02 2.72707245e+02 5.37844727e+02 2.72384155e+02
    2.81451385e+02 3.21745056e+02 3.31803406e+02 3.21587494e+02
    3.82454163e+02 3.21374451e+02 4.32861847e+02 3.21104187e+02
    4.83319000e+02 3.20695892e+02 5.33996887e+02 3.20335388e+02
    2.77868835e+02 1.14304489e+02 3.31712982e+02 1.13887047e+02
    3.86128265e+02 1.13166039e+02 4.40223846e+02 1.12818939e+02
    4.94544189e+02 1.12090111e+02 5.48622986e+02 1.11537376e+02
    2.79624878e+02 1.67841019e+02 3.32767334e+02 1.67426620e+02
    3.85953033e+02 1.66880585e+02 4.39279297e+02 1.66388840e+02
    4.92242371e+02 1.65903595e+02 5.45486145e+02 1.65458923e+02
    2.81618988e+02 2.19173431e+02 3.33626984e+02 2.18946533e+02
    3.85917328e+02 2.18475327e+02 4.37973022e+02 2.18093185e+02
    4.89953979e+02 2.17554642e+02 5.42325745e+02 2.17000137e+02
    2.83389374e+02 2.68497620e+02 3.34449646e+02 2.68397156e+02
    3.85551849e+02 2.68168793e+02 4.36738770e+02 2.67765991e+02
    4.87779083e+02 2.67181244e+02 5.39074097e+02 2.66882996e+02
    2.85244171e+02 3.15993652e+02 3.35212067e+02 3.15896484e+02
    3.85322388e+02 3.15725830e+02 4.35471832e+02 3.15458771e+02
    4.85513824e+02 3.15180023e+02 5.35796326e+02 3.14696228e+02
    2.78125519e+02 1.08643311e+02 3.32046173e+02 1.07947342e+02
    3.86291809e+02 1.07166321e+02 4.40543152e+02 1.06440193e+02
    4.94640411e+02 1.05578880e+02 5.48733276e+02 1.04981453e+02
    2.79863159e+02 1.62516418e+02 3.32741364e+02 1.61881836e+02
    3.86039581e+02 1.61253403e+02 4.39265564e+02 1.60529175e+02
    4.92218811e+02 1.59774567e+02 5.45603333e+02 1.59100418e+02
    2.81611938e+02 2.14253342e+02 3.33527435e+02 2.13746292e+02
    3.85698700e+02 2.13238647e+02 4.37755554e+02 2.12543182e+02
    4.89847229e+02 2.11745544e+02 5.42073242e+02 2.11211151e+02
    2.83342377e+02 2.63886261e+02 3.34319305e+02 2.63574463e+02
    3.85399719e+02 2.63135712e+02 4.36414093e+02 2.62555084e+02
    4.87443817e+02 2.61800659e+02 5.38714417e+02 2.61389984e+02
    2.84935974e+02 3.11684387e+02 3.34918518e+02 3.11442047e+02
    3.85135925e+02 3.11063599e+02 4.35156982e+02 3.10601746e+02
    4.85100128e+02 3.09986908e+02 5.35463074e+02 3.09435699e+02
    2.78303009e+02 1.09595734e+02 3.32073517e+02 1.08716225e+02
    3.86002045e+02 1.07742584e+02 4.40114349e+02 1.06931213e+02
    4.93976501e+02 1.06003403e+02 5.48002136e+02 1.05289810e+02
    2.80358063e+02 1.63158691e+02 3.33139282e+02 1.62419907e+02
    3.86114746e+02 1.61623718e+02 4.39242615e+02 1.60808624e+02
    4.92069977e+02 1.59972626e+02 5.45232544e+02 1.59147110e+02
    2.82363647e+02 2.14623123e+02 3.34138550e+02 2.14252106e+02
    3.86163513e+02 2.13394775e+02 4.38090118e+02 2.12659012e+02
    4.90005981e+02 2.11819290e+02 5.42175720e+02 2.11038101e+02
    2.84222321e+02 2.64350159e+02 3.35001740e+02 2.63874664e+02
    3.86184479e+02 2.63269409e+02 4.37099243e+02 2.62602142e+02
    4.87920441e+02 2.61769897e+02 5.39241943e+02 2.61178925e+02
    2.86121338e+02 3.12075348e+02 3.35904388e+02 3.11596497e+02
    3.85989319e+02 3.11183350e+02 4.35980377e+02 3.10575073e+02
    4.85886963e+02 3.09933319e+02 5.36233093e+02 3.09269623e+02
    2.75983734e+02 1.14249260e+02 3.29347443e+02 1.13405746e+02
    3.82771149e+02 1.12538193e+02 4.36504944e+02 1.11745064e+02
    4.89843933e+02 1.11070580e+02 5.43363220e+02 1.10284859e+02
    2.77908661e+02 1.67410156e+02 3.30351898e+02 1.66657562e+02
    3.82886200e+02 1.66012024e+02 4.35579559e+02 1.65343048e+02
    4.87938080e+02 1.64473160e+02 5.40689270e+02 1.63687469e+02
    2.79768219e+02 2.18579010e+02 3.31321899e+02 2.18248901e+02
    3.82933960e+02 2.17482880e+02 4.34557861e+02 2.16798737e+02
    4.86188995e+02 2.16104645e+02 5.37892700e+02 2.15377792e+02
    2.81544922e+02 2.68114746e+02 3.32180603e+02 2.67692474e+02
    3.82857635e+02 2.67197754e+02 4.33598419e+02 2.66492340e+02
    4.84255646e+02 2.65756226e+02 5.35044922e+02 2.65247925e+02
    2.83395508e+02 3.15752899e+02 3.33080597e+02 3.15360107e+02
    3.82792175e+02 3.14970306e+02 4.32638855e+02 3.14452972e+02
    4.82367340e+02 3.13751068e+02 5.32310242e+02 3.13210999e+02
    3.24634918e+02 9.72034302e+01 3.73765503e+02 9.21753387e+01
    4.25372772e+02 8.66304321e+01 4.79172546e+02 8.10824814e+01
    5.35403625e+02 7.52996140e+01 5.93937378e+02 6.97510757e+01
    3.27489410e+02 1.48762878e+02 3.76302155e+02 1.44769608e+02
    4.27616455e+02 1.40732635e+02 4.81221680e+02 1.36329269e+02
    5.37195007e+02 1.32090027e+02 5.95817383e+02 1.27474709e+02
    3.30468231e+02 1.99614914e+02 3.78827454e+02 1.96907501e+02
    4.29931824e+02 1.94057785e+02 4.83204254e+02 1.91144333e+02
    5.39042236e+02 1.87955719e+02 5.97148682e+02 1.84758072e+02
    3.33222565e+02 2.49960938e+02 3.81596588e+02 2.48352661e+02
    4.32210449e+02 2.46884003e+02 4.85241455e+02 2.45122055e+02
    5.40548767e+02 2.43248352e+02 5.98456055e+02 2.41456238e+02
    3.36132751e+02 2.99510468e+02 3.84260406e+02 2.99146942e+02
    4.34484741e+02 2.98762482e+02 4.87160919e+02 2.98357849e+02
    5.42148132e+02 2.97806427e+02 5.99533569e+02 2.97109558e+02
    3.14291443e+02 3.56047882e+02 2.75411926e+02 3.59010590e+02
    2.33796310e+02 3.62145874e+02 1.89512070e+02 3.65454193e+02
    1.41953384e+02 3.68765442e+02 9.08865967e+01 3.72387543e+02
    3.16623291e+02 3.13058228e+02 2.77655273e+02 3.14598297e+02
    2.35855927e+02 3.16237976e+02 1.91538681e+02 3.18020569e+02
    1.43834778e+02 3.19809448e+02 9.25293350e+01 3.21756256e+02
    3.18833862e+02 2.69531097e+02 2.79616028e+02 2.69703522e+02
    2.37862503e+02 2.69910339e+02 1.93422562e+02 2.70150299e+02
    1.45517029e+02 2.70333160e+02 9.40181503e+01 2.70505524e+02
    3.20592438e+02 2.25783157e+02 2.81633301e+02 2.24557312e+02
    2.39746735e+02 2.23328293e+02 1.95225800e+02 2.21842850e+02
    1.46983597e+02 2.20385040e+02 9.53641510e+01 2.18702927e+02
    3.22655701e+02 1.81729401e+02 2.83553436e+02 1.79097839e+02
    2.41483658e+02 1.76277496e+02 1.96870926e+02 1.73276428e+02
    1.48460175e+02 1.69943161e+02 9.68008652e+01 1.66588791e+02
    4.46641296e+02 3.89460724e+02 3.93431122e+02 3.88549530e+02
    3.39549316e+02 3.87479980e+02 2.85049683e+02 3.86593811e+02
    2.29572708e+02 3.85366943e+02 1.73421570e+02 3.84235779e+02
    4.50448059e+02 3.38146210e+02 3.96945831e+02 3.36894104e+02
    3.42305664e+02 3.35618103e+02 2.87128662e+02 3.34202362e+02
    2.31074677e+02 3.32604523e+02 1.74150635e+02 3.31077362e+02
    4.54730530e+02 2.85380280e+02 4.00457581e+02 2.83700928e+02
    3.45218964e+02 2.81991669e+02 2.89285919e+02 2.80298828e+02
    2.32505371e+02 2.78309692e+02 1.74806412e+02 2.76365814e+02
    4.58879181e+02 2.31346878e+02 4.04004639e+02 2.29264343e+02
    3.47989624e+02 2.27125305e+02 2.91420502e+02 2.24933578e+02
    2.33873245e+02 2.22561630e+02 1.75506714e+02 2.20245193e+02
    4.63193726e+02 1.75874039e+02 4.07263885e+02 1.73413788e+02
    3.50838959e+02 1.70694702e+02 2.93579224e+02 1.68254059e+02
    2.35358734e+02 1.65375046e+02 1.76217148e+02 1.62773529e+02
    4.51379669e+02 3.79384338e+02 3.95608307e+02 3.78493835e+02
    3.38651520e+02 3.77526642e+02 2.80722809e+02 3.76612122e+02
    2.21560959e+02 3.75522308e+02 1.60968185e+02 3.74458252e+02
    4.56155853e+02 3.24104248e+02 3.99833099e+02 3.22748352e+02
    3.42223114e+02 3.21296265e+02 2.83510956e+02 3.19716125e+02
    2.23486603e+02 3.18046326e+02 1.62236389e+02 3.16336578e+02
    4.61187683e+02 2.67413330e+02 4.04184540e+02 2.65453857e+02
    3.45709167e+02 2.63363373e+02 2.86408813e+02 2.61205658e+02
    2.25520554e+02 2.58805939e+02 1.63453232e+02 2.56543365e+02
    4.66125153e+02 2.09310074e+02 4.08529724e+02 2.06608917e+02
    3.49436523e+02 2.03801636e+02 2.89324280e+02 2.01052994e+02
    2.27714111e+02 1.98200958e+02 1.64787598e+02 1.95234619e+02
    4.71083771e+02 1.49572495e+02 4.12744720e+02 1.46221848e+02
    3.53005981e+02 1.42736160e+02 2.92186279e+02 1.39385590e+02
    2.29965363e+02 1.35785858e+02 1.66207306e+02 1.32303925e+02
    3.80358429e+02 3.80993927e+02 3.27472168e+02 3.79811768e+02
    2.73002411e+02 3.78594604e+02 2.17227692e+02 3.77341370e+02
    1.59586807e+02 3.75912598e+02 1.00200760e+02 3.74368652e+02
    3.83858002e+02 3.27822815e+02 3.31054749e+02 3.25934143e+02
    2.76329407e+02 3.23898956e+02 2.20280533e+02 3.21804047e+02
    1.62362930e+02 3.19575653e+02 1.02783218e+02 3.17167450e+02
    3.87593689e+02 2.74229492e+02 3.34500977e+02 2.71471588e+02
    2.79618774e+02 2.68575226e+02 2.23413040e+02 2.65717590e+02
    1.65323364e+02 2.62557343e+02 1.05477005e+02 2.59444611e+02
    3.91250458e+02 2.20167480e+02 3.38032135e+02 2.16509277e+02
    2.83061554e+02 2.12788818e+02 2.26642120e+02 2.09041855e+02
    1.68338150e+02 2.05253006e+02 1.08303200e+02 2.01210876e+02
    3.94854919e+02 1.65534592e+02 3.41488434e+02 1.61123734e+02
    2.86390747e+02 1.56557739e+02 2.29792831e+02 1.51853638e+02
    1.71353653e+02 1.47223465e+02 1.11149979e+02 1.42364136e+02
    3.24600708e+02 3.40039795e+02 2.78973663e+02 3.37614166e+02
    2.29886017e+02 3.35338043e+02 1.79901001e+02 3.32779144e+02
    1.25768021e+02 3.30131622e+02 7.03774567e+01 3.27490479e+02
    3.28818634e+02 2.91997040e+02 2.82522095e+02 2.88694855e+02
    2.34440720e+02 2.85361847e+02 1.83815842e+02 2.81406189e+02
    1.31641281e+02 2.77855927e+02 7.51101608e+01 2.73541779e+02
    3.31151215e+02 2.44720520e+02 2.86678589e+02 2.40224167e+02
    2.38072571e+02 2.35657272e+02 1.88929550e+02 2.31050186e+02
    1.35804321e+02 2.26070618e+02 8.11672897e+01 2.20941330e+02
    3.34988251e+02 1.97764450e+02 2.89240753e+02 1.92587799e+02
    2.42438507e+02 1.87115524e+02 1.92616852e+02 1.81159622e+02
    1.41322540e+02 1.75451828e+02 8.60372391e+01 1.68765442e+02
    3.36791779e+02 1.51841888e+02 2.92852142e+02 1.45550873e+02
    2.45535767e+02 1.39089996e+02 1.97199326e+02 1.32293213e+02
    1.45050766e+02 1.25014397e+02 9.19993744e+01 1.18078766e+02
    6.38306694e+01 3.82028290e+02 7.28291626e+01 3.28356262e+02
    8.13600998e+01 2.74767853e+02 8.99736938e+01 2.21786697e+02
    9.86912460e+01 1.69470596e+02 1.07115837e+02 1.17488480e+02
    1.18253685e+02 3.85609009e+02 1.26845863e+02 3.33540100e+02
    1.35320770e+02 2.81684784e+02 1.43309525e+02 2.30388947e+02
    1.51457794e+02 1.79463989e+02 1.59225998e+02 1.29153549e+02
    1.69239197e+02 3.88773254e+02 1.77601425e+02 3.38242950e+02
    1.85266434e+02 2.88129456e+02 1.92992416e+02 2.38342575e+02
    2.00708710e+02 1.88998718e+02 2.07783600e+02 1.40139404e+02
    2.17313782e+02 3.91781555e+02 2.25179535e+02 3.42749664e+02
    2.32642715e+02 2.94171204e+02 2.39956589e+02 2.45713409e+02
    2.46911041e+02 1.98125656e+02 2.53986694e+02 1.50584534e+02
    2.62515472e+02 3.94490692e+02 2.69938263e+02 3.46991669e+02
    2.76713226e+02 2.99784149e+02 2.83698242e+02 2.52882492e+02
    2.90403503e+02 2.06496368e+02 2.96819580e+02 1.60487228e+02
    4.85741501e+01 3.99115448e+02 5.36271591e+01 3.43004944e+02
    5.87089577e+01 2.86798218e+02 6.40053024e+01 2.30764465e+02
    6.94557495e+01 1.75044296e+02 7.51638641e+01 1.19521118e+02
    1.05189529e+02 3.98713745e+02 1.10178741e+02 3.44590454e+02
    1.15284874e+02 2.90546478e+02 1.20278008e+02 2.36637024e+02
    1.25377846e+02 1.82921997e+02 1.30410446e+02 1.29362152e+02
    1.57579712e+02 3.98135986e+02 1.62567963e+02 3.45925262e+02
    1.67466583e+02 2.93871338e+02 1.72285217e+02 2.42006638e+02
    1.76915588e+02 1.90296555e+02 1.81594742e+02 1.38641830e+02
    2.06763550e+02 3.97567444e+02 2.11465515e+02 3.47265503e+02
    2.16228683e+02 2.97061340e+02 2.20589890e+02 2.46995682e+02
    2.25140869e+02 1.97145767e+02 2.29494827e+02 1.47384521e+02
    2.52431259e+02 3.96857910e+02 2.56965302e+02 3.48391113e+02
    2.61012085e+02 2.99861481e+02 2.65409027e+02 2.51557861e+02
    2.69612793e+02 2.03523209e+02 2.73857178e+02 1.55503174e+02
    5.55329132e+01 3.99327698e+02 6.09818077e+01 3.42821228e+02
    6.63114090e+01 2.86048676e+02 7.16731110e+01 2.29266632e+02
    7.73385468e+01 1.72600174e+02 8.31709442e+01 1.15951408e+02
    1.12441498e+02 3.98954895e+02 1.17753693e+02 3.44373657e+02
    1.23295288e+02 2.89761597e+02 1.28562851e+02 2.35153336e+02
    1.33872086e+02 1.80529922e+02 1.39125061e+02 1.25811844e+02
    1.65244064e+02 3.98238770e+02 1.70541061e+02 3.45657532e+02
    1.75811691e+02 2.93110931e+02 1.80967010e+02 2.40489685e+02
    1.86009506e+02 1.87880356e+02 1.90973663e+02 1.35393646e+02
    2.14617569e+02 3.97535645e+02 2.19751068e+02 3.46784515e+02
    2.24887146e+02 2.96187103e+02 2.29704102e+02 2.45447052e+02
    2.34582672e+02 1.94775482e+02 2.39353928e+02 1.44180298e+02
    2.60416412e+02 3.96808563e+02 2.65538696e+02 3.47923004e+02
    2.70135132e+02 2.99021057e+02 2.74837585e+02 2.50094849e+02
    2.79557281e+02 2.01270966e+02 2.84168427e+02 1.52377457e+02
    5.64398308e+01 4.01154022e+02 6.18055496e+01 3.44626160e+02
    6.71911163e+01 2.87895508e+02 7.25377426e+01 2.31182449e+02
    7.81231689e+01 1.74531494e+02 8.38991623e+01 1.17871872e+02
    1.13360435e+02 4.00666046e+02 1.18651917e+02 3.46070038e+02
    1.24174858e+02 2.91535309e+02 1.29395126e+02 2.36948303e+02
    1.34616745e+02 1.82349655e+02 1.39864639e+02 1.27627037e+02
    1.66109100e+02 3.99782959e+02 1.71404388e+02 3.47351044e+02
    1.76597229e+02 2.94700226e+02 1.81668167e+02 2.42184875e+02
    1.86726151e+02 1.89589691e+02 1.91660019e+02 1.37015381e+02
    2.15480362e+02 3.99088409e+02 2.20558426e+02 3.48457764e+02
    2.25608398e+02 2.97728333e+02 2.30508423e+02 2.47086594e+02
    2.35343002e+02 1.96430588e+02 2.39997177e+02 1.45679718e+02
    2.61261536e+02 3.98305389e+02 2.66295013e+02 3.49460693e+02
    2.70792389e+02 3.00500854e+02 2.75593842e+02 2.51582474e+02
    2.80248505e+02 2.02739227e+02 2.84746338e+02 1.53862091e+02
    5.46710358e+01 4.06594208e+02 6.01791840e+01 3.50206299e+02
    6.55721970e+01 2.93448975e+02 7.12783966e+01 2.36643372e+02
    7.69471207e+01 1.79962006e+02 8.27869339e+01 1.23457405e+02
    1.11493736e+02 4.06172028e+02 1.16980537e+02 3.51588715e+02
    1.22537468e+02 2.97021973e+02 1.27943733e+02 2.42428055e+02
    1.33432587e+02 1.87834579e+02 1.38711853e+02 1.33330338e+02
    1.64287811e+02 4.05408539e+02 1.69664749e+02 3.52814575e+02
    1.75115372e+02 3.00325958e+02 1.80307877e+02 2.47678741e+02
    1.85460403e+02 1.95234146e+02 1.90513077e+02 1.42660355e+02
    2.13653671e+02 4.04628876e+02 2.18834549e+02 3.53930908e+02
    2.24066681e+02 3.03328308e+02 2.29021957e+02 2.52597260e+02
    2.33923965e+02 2.01962051e+02 2.38739517e+02 1.51382370e+02
    2.59434357e+02 4.03840973e+02 2.64555023e+02 3.54928680e+02
    2.69264343e+02 3.06080566e+02 2.74127533e+02 2.57170197e+02
    2.78785797e+02 2.08395737e+02 2.83519409e+02 1.59578140e+02</data></Image_points>
</opencv_storage>
